MANIFEST.in
README.rst
setup.py
doesnothing/__init__.py
doesnothing/command_line.py
doesnothing/data.txt
doesnothing/nada.py
doesnothing.egg-info/PKG-INFO
doesnothing.egg-info/SOURCES.txt
doesnothing.egg-info/dependency_links.txt
doesnothing.egg-info/entry_points.txt
doesnothing.egg-info/requires.txt
doesnothing.egg-info/top_level.txt