Metadata-Version: 1.0
Name: doesnothing
Version: 0.1.4
Summary: This does nothing
Home-page: http://github.com/dlrice/doesnothing
Author: Dan Rice
Author-email: dr9@sanger.ac.uk
License: MIT
Platform: UNKNOWN
